print_bot_gen_1.py
print_bot_gen_1-1.0.1.dist-info/METADATA
print_bot_gen_1-1.0.1.dist-info/WHEEL
print_bot_gen_1-1.0.1.dist-info/entry_points.txt
print_bot_gen_1-1.0.1.dist-info/top_level.txt
print_bot_gen_1-1.0.1.dist-info/RECORD
