Metadata-Version: 2.1
Name: print-bot-gen-1
Version: 1.0.1
Requires-Dist: to-pip
